proman_github/__init__.py
proman_github/__main__.py
proman_github/archive.py
proman_github/cli.py
proman_github/config.py
proman_github/dependency.py
proman_github/package_manager.py
proman_github-0.1.1.dev2.dist-info/entry_points.txt
proman_github-0.1.1.dev2.dist-info/LICENSE
proman_github-0.1.1.dev2.dist-info/WHEEL
proman_github-0.1.1.dev2.dist-info/METADATA
proman_github-0.1.1.dev2.dist-info/RECORD
